pascal_tools/__init__.py
pascal_tools-0.1.3.5.9.dist-info/METADATA
pascal_tools-0.1.3.5.9.dist-info/WHEEL
pascal_tools-0.1.3.5.9.dist-info/top_level.txt
pascal_tools-0.1.3.5.9.dist-info/RECORD
