Metadata-Version: 2.1
Name: pascal-tools
Version: 0.1.3.5.9
Summary: Some useful tools for me ! 
Home-page: https://github.com/moreaupascal56/pascal_tools
Author: Pascal Moreau
Author-email: moreaupascal56@gmail.com
License: free
Platform: UNKNOWN
